pytest_xray_reporter/__init__.py
pytest_xray_reporter/plugin.py
pytest_xray_reporter-0.1.18.dist-info/METADATA
pytest_xray_reporter-0.1.18.dist-info/WHEEL
pytest_xray_reporter-0.1.18.dist-info/entry_points.txt
pytest_xray_reporter-0.1.18.dist-info/licenses/LICENSE
pytest_xray_reporter-0.1.18.dist-info/RECORD
